o2a_registry/__init__.py
o2a_registry/api.py
o2a_registry/py.typed
o2a_registry/rate_limiter.py
o2a_registry/reference_resolver.py
o2a_registry/resolve_query_parameters.py
o2a_registry/rest_adapter.py
o2a_registry/models/__init__.py
o2a_registry/models/all_query.py
o2a_registry/models/contact.py
o2a_registry/models/create_contact.py
o2a_registry/models/create_event.py
o2a_registry/models/create_item.py
o2a_registry/models/create_mission.py
o2a_registry/models/create_mission_item.py
o2a_registry/models/edit_contact.py
o2a_registry/models/edit_event.py
o2a_registry/models/edit_item.py
o2a_registry/models/edit_mission.py
o2a_registry/models/event.py
o2a_registry/models/item.py
o2a_registry/models/item_contact.py
o2a_registry/models/item_reference.py
o2a_registry/models/item_state.py
o2a_registry/models/mission.py
o2a_registry/models/mission_contact.py
o2a_registry/models/vocable.py
o2a_registry/models/vocable_group.py
o2a_registry/models/workflow.py
o2a_registry/utils/__init__.py
o2a_registry/utils/pagination.py
o2a_registry/validation/__init__.py
o2a_registry/validation/url_host_checker.py
o2a_registry_python_lib-0.1.1.dist-info/METADATA
o2a_registry_python_lib-0.1.1.dist-info/WHEEL
o2a_registry_python_lib-0.1.1.dist-info/licenses/LICENSE
o2a_registry_python_lib-0.1.1.dist-info/RECORD
