Metadata-Version: 2.4
Name: o2a.registry.python.lib
Version: 0.1.1
Summary: Basic wrapper around the https://registry.o2a-data.de/api/ powered by pydantic.
Project-URL: Homepage, https://registry.o2a-data.de/
Project-URL: Documentation, https://o2a-data.de/docs/o2a-registry-py/getting_started.html
Project-URL: Repository, https://gitlab.awi.de/o2a/registry/o2a.registry.python.lib.git
Project-URL: Issues, https://gitlab.awi.de/o2a/registry/o2a.registry.python.lib/-/issues
Author-email: Karsten Schimpf <karsten.schimpf@awi.de>
License-Expression: BSD-3-Clause
License-File: LICENSE
Keywords: O2A,api,registry
Classifier: Development Status :: 5 - Production/Stable
Classifier: Intended Audience :: Developers
Classifier: Intended Audience :: Science/Research
Classifier: Natural Language :: English
Classifier: Programming Language :: Python :: 3
Classifier: Programming Language :: Python :: 3.10
Classifier: Programming Language :: Python :: 3.11
Classifier: Programming Language :: Python :: 3.12
Classifier: Programming Language :: Python :: 3.13
Classifier: Topic :: Utilities
Classifier: Typing :: Typed
Requires-Python: >=3.10
Requires-Dist: aiohttp>=3.10.8
Requires-Dist: email-validator>=2.2.0
Requires-Dist: pydantic>=2.9.2
